pika_marker/__init__.py
pika_marker/main.py
pika_marker/pika_marker.py
pika_marker-0.1.0.dist-info/licenses/LICENSE
pika_marker-0.1.0.dist-info/METADATA
pika_marker-0.1.0.dist-info/WHEEL
pika_marker-0.1.0.dist-info/entry_points.txt
pika_marker-0.1.0.dist-info/top_level.txt
pika_marker-0.1.0.dist-info/RECORD
