Metadata-Version: 2.4
Name: pika-marker
Version: 0.1.0
Summary: Python tool to write PIKA marker files
Author-email: Sebastian Döbel <sebastian.doebel@tu-dresden.de>
License-Expression: BSD-3-Clause
Project-URL: Homepage, https://gitlab.hrz.tu-chemnitz.de/pika/pika-marker
Classifier: Programming Language :: Python :: 3
Classifier: Operating System :: OS Independent
Requires-Python: >=3.9
License-File: LICENSE
Dynamic: license-file
